nbkit/__init__.py
nbkit/_modidx.py
nbkit/cmds.py
nbkit/magic/__init__.py
nbkit/magic/skip.py
nbkit/nbs/__init__.py
nbkit/nbs/aggr.py
nbkit/nbs/find.py
nbkit/nbs/load.py
nbkit/nbs/nlog.py
nbkit/nbs/pfix.py
nbkit/nbs/view.py
nbkit/nbs/utils/__init__.py
nbkit/nbs/utils/aggr.py
nbkit/nbs/utils/bool.py
nbkit/nbs/utils/cons.py
nbkit/nbs/utils/defs.py
nbkit/nbs/utils/file.py
nbkit/nbs/utils/misc.py
nbkit/nbs/utils/name.py
nbkit/nbs/utils/node.py
nbkit/nbs/utils/nums.py
nbkit/nbs/utils/pttn.py
nbkit/nbs/utils/show.py
nbkit/nbs/utils/tmpl.py
nbkit/nbs/utils/tsub.py
nbkit-0.0.10.dist-info/LICENSE
nbkit-0.0.10.dist-info/METADATA
nbkit-0.0.10.dist-info/WHEEL
nbkit-0.0.10.dist-info/entry_points.txt
nbkit-0.0.10.dist-info/top_level.txt
nbkit-0.0.10.dist-info/RECORD
