Metadata-Version: 2.1
Name: nbkit
Version: 0.0.10
Summary: jupyter notebook toolkit
Home-page: https://github.com/dsm-72/nbkit
Author: dsm-72
Author-email: sumner.magruder@yale.edu
License: Apache Software License 2.0
Keywords: nbdev jupyter notebook python nbkit
Classifier: Development Status :: 4 - Beta
Classifier: Intended Audience :: Developers
Classifier: Natural Language :: English
Classifier: Programming Language :: Python :: 3.11
Classifier: License :: OSI Approved :: Apache Software License
Requires-Python: >=3.11
License-File: LICENSE
Requires-Dist: nbformat
Requires-Dist: rich
Requires-Dist: typer
Requires-Dist: tqdm
Requires-Dist: nchr
Requires-Dist: nlit
Requires-Dist: chck
Requires-Dist: pstr
Requires-Dist: atyp
Requires-Dist: ropts
Requires-Dist: idfunc
Requires-Dist: ispec
Requires-Dist: ipywidgets
Provides-Extra: dev
